szgo/__init__.py
szgo/engine/__init__.py
szgo/engine/board.py
szgo-0.0.30.dist-info/LICENSE
szgo-0.0.30.dist-info/METADATA
szgo-0.0.30.dist-info/WHEEL
szgo-0.0.30.dist-info/top_level.txt
szgo-0.0.30.dist-info/RECORD
