Metadata-Version: 2.1
Name: szgo
Version: 0.0.30
Summary: Computer Go Board Game
Home-page: https://github.com/twoutlook/szgo
Author: Chenpingling
Author-email: chenpingling@protonmail.com
License: UNKNOWN
Platform: UNKNOWN
Classifier: Programming Language :: Python :: 3
Classifier: License :: OSI Approved :: MIT License
Classifier: Operating System :: OS Independent
